stactools/noaa_c_cap/__init__.py
stactools/noaa_c_cap/commands.py
stactools/noaa_c_cap/constants.py
stactools/noaa_c_cap/dataset.py
stactools/noaa_c_cap/stac.py
stactools/noaa_c_cap/urllist-modres.txt
stactools/noaa_c_cap/utils.py
stactools_noaa_c_cap-0.2.2.dist-info/LICENSE
stactools_noaa_c_cap-0.2.2.dist-info/METADATA
stactools_noaa_c_cap-0.2.2.dist-info/WHEEL
stactools_noaa_c_cap-0.2.2.dist-info/top_level.txt
stactools_noaa_c_cap-0.2.2.dist-info/RECORD
