Metadata-Version: 2.1
Name: stactools-noaa-c-cap
Version: 0.2.2
Summary: Create STAC Items and Collections for NOAA C-CAP data
Home-page: https://github.com/stactools-packages/noaa-c-cap
Author: stac-utils
Author-email: stac@radiant.earth
Project-URL: Documentation, https://stactools-noaa-c-cap.readthedocs.io/en/latest/
Project-URL: Issues, https://github.com/stactools-packages/noaa-c-cap/issues
Keywords: stactools,pystac,catalog,STAC
Classifier: Development Status :: 4 - Beta
Classifier: License :: OSI Approved :: Apache Software License
Classifier: Programming Language :: Python :: 3.7
Classifier: Programming Language :: Python :: 3.8
Classifier: Programming Language :: Python :: 3.9
License-File: LICENSE
Requires-Dist: stactools (>=0.3.0)
Requires-Dist: pystac (>=1.3.0)
